gdistcc/__init__.py
gdistcc/__main__.py
gdistcc/gdistcc.py
gdistcc/settings.json
gdistcc/startup-scripts/__init__.py
gdistcc/startup-scripts/centos-7.sh
gdistcc/startup-scripts/debian-8.sh
gdistcc/startup-scripts/ubuntu-1404-lts.sh
gdistcc/startup-scripts/ubuntu-1604-lts.sh
gdistcc-0.9.3.post3.dist-info/DESCRIPTION.rst
gdistcc-0.9.3.post3.dist-info/METADATA
gdistcc-0.9.3.post3.dist-info/RECORD
gdistcc-0.9.3.post3.dist-info/WHEEL
gdistcc-0.9.3.post3.dist-info/entry_points.txt
gdistcc-0.9.3.post3.dist-info/metadata.json
gdistcc-0.9.3.post3.dist-info/top_level.txt
