Metadata-Version: 2.0
Name: gdistcc
Version: 0.9.3.post3
Summary: gdistcc: the easy way to compile in the cloud!
Home-page: https://github.com/apeabody/gdistcc
Author: Andrew Peabody
Author-email: apeabody@gmail.com
License: APACHE
Keywords: google compute engine distcc make
Platform: UNKNOWN
Classifier: Development Status :: 3 - Alpha
Classifier: Intended Audience :: Developers
Classifier: Topic :: Software Development :: Build Tools
Classifier: License :: OSI Approved :: Apache Software License
Classifier: Programming Language :: Python :: 2
Classifier: Programming Language :: Python :: 2.7
Classifier: Programming Language :: Python :: 3
Classifier: Programming Language :: Python :: 3.5
Requires-Dist: google-api-python-client
Requires-Dist: six
